<?xml version="1.0" encoding="utf-8"?>
<LanguageData>
  <!-- SPECIAL: Blueprint and Frame of Terrian, generated by RimTrans -->
  <LingGelFloor_Normal_Blueprint.label>Gel flooring (blueprint)</LingGelFloor_Normal_Blueprint.label>
  <LingGelFloor_Normal_Frame.label>Gel flooring (Under construction)</LingGelFloor_Normal_Frame.label>
  <LingGelFloor_Normal_Frame.description>Flooring under construction</LingGelFloor_Normal_Frame.description>
  <LingGelFloor_Wood_Blueprint.label>Wood grain gel flooring (blueprint)</LingGelFloor_Wood_Blueprint.label>
  <LingGelFloor_Wood_Frame.label>Wood grain gel flooring (Under construction)</LingGelFloor_Wood_Frame.label>
  <LingGelFloor_Wood_Frame.description>Flooring under construction</LingGelFloor_Wood_Frame.description>
  <LingGelFloor_Rough_Blueprint.label>Coarse ground gel flooring (blueprint)</LingGelFloor_Rough_Blueprint.label>
  <LingGelFloor_Rough_Frame.label>Coarse ground gel flooring (Under construction)</LingGelFloor_Rough_Frame.label>
  <LingGelFloor_Rough_Frame.description>Flooring under construction</LingGelFloor_Rough_Frame.description>
  <LingGelFloor_Smooth_Blueprint.label>Sanding the gel floor (blueprint)</LingGelFloor_Smooth_Blueprint.label>
  <LingGelFloor_Smooth_Frame.label>Sanding the gel floor (Under construction)</LingGelFloor_Smooth_Frame.label>
  <LingGelFloor_Smooth_Frame.description>Flooring under construction</LingGelFloor_Smooth_Frame.description>
  <LingGelFloor_Brick_Blueprint.label>Brick type gel floor (blueprint)</LingGelFloor_Brick_Blueprint.label>
  <LingGelFloor_Brick_Frame.label>Brick type gel floor (Under construction)</LingGelFloor_Brick_Frame.label>
  <LingGelFloor_Brick_Frame.description>Flooring under construction</LingGelFloor_Brick_Frame.description>
  <LingGelFloor_Fine_Blueprint.label>Delicate gel flooring (blueprint)</LingGelFloor_Fine_Blueprint.label>
  <LingGelFloor_Fine_Frame.label>Delicate gel flooring (Under construction)</LingGelFloor_Fine_Frame.label>
  <LingGelFloor_Fine_Frame.description>Flooring under construction</LingGelFloor_Fine_Frame.description>
  <LingGelFloor_Carpet_Blueprint.label>Patterned gel floor (blueprint)</LingGelFloor_Carpet_Blueprint.label>
  <LingGelFloor_Carpet_Frame.label>Patterned gel floor (Under construction)</LingGelFloor_Carpet_Frame.label>
  <LingGelFloor_Carpet_Frame.description>Flooring under construction</LingGelFloor_Carpet_Frame.description>
  <LingGelFloor_Water_Blueprint.label>Hydrogel flooring (blueprint)</LingGelFloor_Water_Blueprint.label>
  <LingGelFloor_Water_Frame.label>Hydrogel flooring (Under construction)</LingGelFloor_Water_Frame.label>
  <LingGelFloor_Water_Frame.description>Flooring under construction</LingGelFloor_Water_Frame.description>
  <LingGelFloor_Soil_Blueprint.label>Plant gel flooring (blueprint)</LingGelFloor_Soil_Blueprint.label>
  <LingGelFloor_Soil_Frame.label>Plant gel flooring (Under construction)</LingGelFloor_Soil_Frame.label>
  <LingGelFloor_Soil_Frame.description>Flooring under construction</LingGelFloor_Soil_Frame.description>
  <!--<LingGelFloor_Blueprint.label>凝胶地板(blueprint)</LingGelFloor_Blueprint.label>-->
  <!--<LingGelFloor_Frame.label>凝胶地板(建造中)</LingGelFloor_Frame.label>-->
  <!--<LingGelFloor_Frame.description>.</LingGelFloor_Frame.description>-->
</LanguageData>